{
	"elements": [
		{
			"element": {
				"element_type": "structure_gel:gel_single_pool_element",
				"ignoreEntities": false,
				"location": "blue_skies:village/crystal_dunes/streets/straight_1",
				"maintainWater": true,
				"processors": "blue_skies:crystal_dunes_street",
				"projection": "terrain_matching"
			},
			"weight": 10
		},
		{
			"element": {
				"element_type": "structure_gel:gel_single_pool_element",
				"ignoreEntities": false,
				"location": "blue_skies:village/crystal_dunes/streets/straight_0",
				"maintainWater": true,
				"processors": "blue_skies:crystal_dunes_street",
				"projection": "terrain_matching"
			},
			"weight": 10
		},
		{
			"element": {
				"element_type": "structure_gel:gel_single_pool_element",
				"ignoreEntities": false,
				"location": "blue_skies:village/crystal_dunes/streets/straight_3",
				"maintainWater": true,
				"processors": "blue_skies:crystal_dunes_street",
				"projection": "terrain_matching"
			},
			"weight": 10
		},
		{
			"element": {
				"element_type": "structure_gel:gel_single_pool_element",
				"ignoreEntities": false,
				"location": "blue_skies:village/crystal_dunes/streets/straight_2",
				"maintainWater": true,
				"processors": "blue_skies:crystal_dunes_street",
				"projection": "terrain_matching"
			},
			"weight": 10
		},
		{
			"element": {
				"element_type": "structure_gel:gel_single_pool_element",
				"ignoreEntities": false,
				"location": "blue_skies:village/crystal_dunes/streets/straight_5",
				"maintainWater": true,
				"processors": "blue_skies:crystal_dunes_street",
				"projection": "terrain_matching"
			},
			"weight": 10
		},
		{
			"element": {
				"element_type": "structure_gel:gel_single_pool_element",
				"ignoreEntities": false,
				"location": "blue_skies:village/crystal_dunes/streets/straight_4",
				"maintainWater": true,
				"processors": "blue_skies:crystal_dunes_street",
				"projection": "terrain_matching"
			},
			"weight": 10
		},
		{
			"element": {
				"element_type": "structure_gel:gel_single_pool_element",
				"ignoreEntities": false,
				"location": "blue_skies:village/crystal_dunes/streets/corner_1",
				"maintainWater": true,
				"processors": "blue_skies:crystal_dunes_street",
				"projection": "terrain_matching"
			},
			"weight": 8
		},
		{
			"element": {
				"element_type": "structure_gel:gel_single_pool_element",
				"ignoreEntities": false,
				"location": "blue_skies:village/crystal_dunes/streets/corner_2",
				"maintainWater": true,
				"processors": "blue_skies:crystal_dunes_street",
				"projection": "terrain_matching"
			},
			"weight": 8
		},
		{
			"element": {
				"element_type": "structure_gel:gel_single_pool_element",
				"ignoreEntities": false,
				"location": "blue_skies:village/crystal_dunes/streets/corner_0",
				"maintainWater": true,
				"processors": "blue_skies:crystal_dunes_street",
				"projection": "terrain_matching"
			},
			"weight": 8
		},
		{
			"element": {
				"element_type": "structure_gel:gel_single_pool_element",
				"ignoreEntities": false,
				"location": "blue_skies:village/crystal_dunes/streets/intersection_5",
				"maintainWater": true,
				"processors": "blue_skies:crystal_dunes_street",
				"projection": "terrain_matching"
			},
			"weight": 2
		},
		{
			"element": {
				"element_type": "structure_gel:gel_single_pool_element",
				"ignoreEntities": false,
				"location": "blue_skies:village/crystal_dunes/streets/intersection_2",
				"maintainWater": true,
				"processors": "blue_skies:crystal_dunes_street",
				"projection": "terrain_matching"
			},
			"weight": 2
		},
		{
			"element": {
				"element_type": "structure_gel:gel_single_pool_element",
				"ignoreEntities": false,
				"location": "blue_skies:village/crystal_dunes/streets/intersection_1",
				"maintainWater": true,
				"processors": "blue_skies:crystal_dunes_street",
				"projection": "terrain_matching"
			},
			"weight": 2
		},
		{
			"element": {
				"element_type": "structure_gel:gel_single_pool_element",
				"ignoreEntities": false,
				"location": "blue_skies:village/crystal_dunes/streets/intersection_4",
				"maintainWater": true,
				"processors": "blue_skies:crystal_dunes_street",
				"projection": "terrain_matching"
			},
			"weight": 2
		},
		{
			"element": {
				"element_type": "structure_gel:gel_single_pool_element",
				"ignoreEntities": false,
				"location": "blue_skies:village/crystal_dunes/streets/intersection_3",
				"maintainWater": true,
				"processors": "blue_skies:crystal_dunes_street",
				"projection": "terrain_matching"
			},
			"weight": 2
		},
		{
			"element": {
				"element_type": "structure_gel:gel_single_pool_element",
				"ignoreEntities": false,
				"location": "blue_skies:village/crystal_dunes/streets/intersection_0",
				"maintainWater": true,
				"processors": "blue_skies:crystal_dunes_street",
				"projection": "terrain_matching"
			},
			"weight": 2
		}
	],
	"fallback": "blue_skies:village/crystal_dunes/terminators",
	"name": "blue_skies:village/crystal_dunes/streets"
}